wow_ocr/__init__.py
wow_ocr/detector.py
wow_ocr/pipeline.py
wow_ocr/recognizer.py
wow_ocr/tools.py
wow_ocr-0.0.3.dist-info/LICENSE
wow_ocr-0.0.3.dist-info/METADATA
wow_ocr-0.0.3.dist-info/WHEEL
wow_ocr-0.0.3.dist-info/top_level.txt
wow_ocr-0.0.3.dist-info/RECORD
