Metadata-Version: 2.1
Name: wow-ocr
Version: 0.0.3
Summary: A packaged OCR model to read texts into WoW screenshots
Author-email: Geo <geoffrey.menon38@gmail.com>
License: Permission is hereby granted, free of charge, to any person obtaining a copy
Project-URL: Homepage, https://github.com/geo-tp/wow-ocr
Keywords: ocr,wow,screenshot
Classifier: License :: OSI Approved :: MIT License
Classifier: Programming Language :: Python
Classifier: Programming Language :: Python :: 3
Requires-Python: >=3.9
License-File: LICENSE
Requires-Dist: validators
Requires-Dist: essential-generators
Requires-Dist: tqdm
Requires-Dist: imgaug
Requires-Dist: fonttools
Requires-Dist: editdistance
Requires-Dist: pyclipper
Requires-Dist: shapely
Requires-Dist: efficientnet
Requires-Dist: tensorflow
Provides-Extra: dev
Requires-Dist: black ; extra == 'dev'
Requires-Dist: pip-tools ; extra == 'dev'
Requires-Dist: pytest ; extra == 'dev'
Requires-Dist: types-requests ; extra == 'dev'
Requires-Dist: types-pkg-resources ; extra == 'dev'
